Workbook

Sheet Overview
A2: BankPulse · Banking complaints
A4: 2024-10 through 2026-09 · snapshot 2026-10-19
A6: Selected product | C6: ='Analysis'!B4 -> All products
A8: Complaints | D8: Timely response | G8: Known status | J8: Unknown status
A9: ='Analysis'!B35 -> 351490 | D9: ='Analysis'!E35 -> 0.99286751 | G9: ='Analysis'!D35 -> 351490 | J9: ='Analysis'!B35-'Analysis'!D35 -> 0
A30: Change the product selector on Analysis. Capacity assumptions are editable on Capacity.
A32: Published complaints are not customer complaint rates. Recent complete months may backfill.

Sheet Analysis
A2: Monthly analysis
A4: Product | B4: All products
A6: Product selection controls full-population totals; rates exclude unknown statuses.
A8: Month | B8: Complaints | C8: Timely Yes | D8: Known status | E8: Timely rate | F8: Monthly change % | G8: Chart month | I8: Detail checks | J8: 500-record extract
A9: 2024-10-01T00:00:00.000Z | B9: =IF($B$4="All products",SUMIFS('Monthly Source'!$C$8:$C$55,'Monthly Source'!$A$8:$A$55,$A9),SUMIFS('Monthly Source'!$C$8:$C$55,'Monthly Source'!$A$8:$A$55,$A9,'Monthly Source'!$B$8:$B$55,$B$4)) -> 11868 | C9: =IF($B$4="All products",SUMIFS('Monthly Source'!$D$8:$D$55,'Monthly Source'!$A$8:$A$55,$A9),SUMIFS('Monthly Source'!$D$8:$D$55,'Monthly Source'!$A$8:$A$55,$A9,'Monthly Source'!$B$8:$B$55,$B$4)) -> 11833 | D9: =IF($B$4="All products",SUMIFS('Monthly Source'!$E$8:$E$55,'Monthly Source'!$A$8:$A$55,$A9),SUMIFS('Monthly Source'!$E$8:$E$55,'Monthly Source'!$A$8:$A$55,$A9,'Monthly Source'!$B$8:$B$55,$B$4)) -> 11868 | E9: =IF(D9=0,"n.a.",C9/D9) -> 0.99705089 | F9: n.a. | G9: =TEXT(A9,"mmm yyyy") -> Oct 2024 | I9: Record count | J9: =COUNTA(Detail!A8:A507) -> 500
A10: 2024-11-01T00:00:00.000Z | B10: =IF($B$4="All products",SUMIFS('Monthly Source'!$C$8:$C$55,'Monthly Source'!$A$8:$A$55,$A10),SUMIFS('Monthly Source'!$C$8:$C$55,'Monthly Source'!$A$8:$A$55,$A10,'Monthly Source'!$B$8:$B$55,$B$4)) -> 11270 | C10: =IF($B$4="All products",SUMIFS('Monthly Source'!$D$8:$D$55,'Monthly Source'!$A$8:$A$55,$A10),SUMIFS('Monthly Source'!$D$8:$D$55,'Monthly Source'!$A$8:$A$55,$A10,'Monthly Source'!$B$8:$B$55,$B$4)) -> 11241 | D10: =IF($B$4="All products",SUMIFS('Monthly Source'!$E$8:$E$55,'Monthly Source'!$A$8:$A$55,$A10),SUMIFS('Monthly Source'!$E$8:$E$55,'Monthly Source'!$A$8:$A$55,$A10,'Monthly Source'!$B$8:$B$55,$B$4)) -> 11270 | E10: =IF(D10=0,"n.a.",C10/D10) -> 0.9974268 | F10: =IF(B9=0,"n.a.",B10/B9-1) -> -0.050387597 | G10: =TEXT(A10,"mmm yyyy") -> Nov 2024 | I10: Timely Yes | J10: =COUNTIFS(Detail!G8:G507,"Yes") -> 500
A11: 2024-12-01T00:00:00.000Z | B11: =IF($B$4="All products",SUMIFS('Monthly Source'!$C$8:$C$55,'Monthly Source'!$A$8:$A$55,$A11),SUMIFS('Monthly Source'!$C$8:$C$55,'Monthly Source'!$A$8:$A$55,$A11,'Monthly Source'!$B$8:$B$55,$B$4)) -> 11495 | C11: =IF($B$4="All products",SUMIFS('Monthly Source'!$D$8:$D$55,'Monthly Source'!$A$8:$A$55,$A11),SUMIFS('Monthly Source'!$D$8:$D$55,'Monthly Source'!$A$8:$A$55,$A11,'Monthly Source'!$B$8:$B$55,$B$4)) -> 11467 | D11: =IF($B$4="All products",SUMIFS('Monthly Source'!$E$8:$E$55,'Monthly Source'!$A$8:$A$55,$A11),SUMIFS('Monthly Source'!$E$8:$E$55,'Monthly Source'!$A$8:$A$55,$A11,'Monthly Source'!$B$8:$B$55,$B$4)) -> 11495 | E11: =IF(D11=0,"n.a.",C11/D11) -> 0.99756416 | F11: =IF(B10=0,"n.a.",B11/B10-1) -> 0.019964508 | G11: =TEXT(A11,"mmm yyyy") -> Dec 2024 | I11: Not timely | J11: =COUNTIFS(Detail!G8:G507,"No") -> 0
A12: 2025-01-01T00:00:00.000Z | B12: =IF($B$4="All products",SUMIFS('Monthly Source'!$C$8:$C$55,'Monthly Source'!$A$8:$A$55,$A12),SUMIFS('Monthly Source'!$C$8:$C$55,'Monthly Source'!$A$8:$A$55,$A12,'Monthly Source'!$B$8:$B$55,$B$4)) -> 27440 | C12: =IF($B$4="All products",SUMIFS('Monthly Source'!$D$8:$D$55,'Monthly Source'!$A$8:$A$55,$A12),SUMIFS('Monthly Source'!$D$8:$D$55,'Monthly Source'!$A$8:$A$55,$A12,'Monthly Source'!$B$8:$B$55,$B$4)) -> 27376 | D12: =IF($B$4="All products",SUMIFS('Monthly Source'!$E$8:$E$55,'Monthly Source'!$A$8:$A$55,$A12),SUMIFS('Monthly Source'!$E$8:$E$55,'Monthly Source'!$A$8:$A$55,$A12,'Monthly Source'!$B$8:$B$55,$B$4)) -> 27440 | E12: =IF(D12=0,"n.a.",C12/D12) -> 0.99766764 | F12: =IF(B11=0,"n.a.",B12/B11-1) -> 1.3871248 | G12: =TEXT(A12,"mmm yyyy") -> Jan 2025
A13: 2025-02-01T00:00:00.000Z | B13: =IF($B$4="All products",SUMIFS('Monthly Source'!$C$8:$C$55,'Monthly Source'!$A$8:$A$55,$A13),SUMIFS('Monthly Source'!$C$8:$C$55,'Monthly Source'!$A$8:$A$55,$A13,'Monthly Source'!$B$8:$B$55,$B$4)) -> 11665 | C13: =IF($B$4="All products",SUMIFS('Monthly Source'!$D$8:$D$55,'Monthly Source'!$A$8:$A$55,$A13),SUMIFS('Monthly Source'!$D$8:$D$55,'Monthly Source'!$A$8:$A$55,$A13,'Monthly Source'!$B$8:$B$55,$B$4)) -> 11619 | D13: =IF($B$4="All products",SUMIFS('Monthly Source'!$E$8:$E$55,'Monthly Source'!$A$8:$A$55,$A13),SUMIFS('Monthly Source'!$E$8:$E$55,'Monthly Source'!$A$8:$A$55,$A13,'Monthly Source'!$B$8:$B$55,$B$4)) -> 11665 | E13: =IF(D13=0,"n.a.",C13/D13) -> 0.99605658 | F13: =IF(B12=0,"n.a.",B13/B12-1) -> -0.57489067 | G13: =TEXT(A13,"mmm yyyy") -> Feb 2025 | I13: Independent full-population controls
A14: 2025-03-01T00:00:00.000Z | B14: =IF($B$4="All products",SUMIFS('Monthly Source'!$C$8:$C$55,'Monthly Source'!$A$8:$A$55,$A14),SUMIFS('Monthly Source'!$C$8:$C$55,'Monthly Source'!$A$8:$A$55,$A14,'Monthly Source'!$B$8:$B$55,$B$4)) -> 11325 | C14: =IF($B$4="All products",SUMIFS('Monthly Source'!$D$8:$D$55,'Monthly Source'!$A$8:$A$55,$A14),SUMIFS('Monthly Source'!$D$8:$D$55,'Monthly Source'!$A$8:$A$55,$A14,'Monthly Source'!$B$8:$B$55,$B$4)) -> 11288 | D14: =IF($B$4="All products",SUMIFS('Monthly Source'!$E$8:$E$55,'Monthly Source'!$A$8:$A$55,$A14),SUMIFS('Monthly Source'!$E$8:$E$55,'Monthly Source'!$A$8:$A$55,$A14,'Monthly Source'!$B$8:$B$55,$B$4)) -> 11325 | E14: =IF(D14=0,"n.a.",C14/D14) -> 0.99673289 | F14: =IF(B13=0,"n.a.",B14/B13-1) -> -0.029147021 | G14: =TEXT(A14,"mmm yyyy") -> Mar 2025 | I14: Expected count | J14: 351490
A15: 2025-04-01T00:00:00.000Z | B15: =IF($B$4="All products",SUMIFS('Monthly Source'!$C$8:$C$55,'Monthly Source'!$A$8:$A$55,$A15),SUMIFS('Monthly Source'!$C$8:$C$55,'Monthly Source'!$A$8:$A$55,$A15,'Monthly Source'!$B$8:$B$55,$B$4)) -> 12126 | C15: =IF($B$4="All products",SUMIFS('Monthly Source'!$D$8:$D$55,'Monthly Source'!$A$8:$A$55,$A15),SUMIFS('Monthly Source'!$D$8:$D$55,'Monthly Source'!$A$8:$A$55,$A15,'Monthly Source'!$B$8:$B$55,$B$4)) -> 12071 | D15: =IF($B$4="All products",SUMIFS('Monthly Source'!$E$8:$E$55,'Monthly Source'!$A$8:$A$55,$A15),SUMIFS('Monthly Source'!$E$8:$E$55,'Monthly Source'!$A$8:$A$55,$A15,'Monthly Source'!$B$8:$B$55,$B$4)) -> 12126 | E15: =IF(D15=0,"n.a.",C15/D15) -> 0.99546429 | F15: =IF(B14=0,"n.a.",B15/B14-1) -> 0.070728477 | G15: =TEXT(A15,"mmm yyyy") -> Apr 2025 | I15: Expected Yes | J15: 348983
A16: 2025-05-01T00:00:00.000Z | B16: =IF($B$4="All products",SUMIFS('Monthly Source'!$C$8:$C$55,'Monthly Source'!$A$8:$A$55,$A16),SUMIFS('Monthly Source'!$C$8:$C$55,'Monthly Source'!$A$8:$A$55,$A16,'Monthly Source'!$B$8:$B$55,$B$4)) -> 12909 | C16: =IF($B$4="All products",SUMIFS('Monthly Source'!$D$8:$D$55,'Monthly Source'!$A$8:$A$55,$A16),SUMIFS('Monthly Source'!$D$8:$D$55,'Monthly Source'!$A$8:$A$55,$A16,'Monthly Source'!$B$8:$B$55,$B$4)) -> 12858 | D16: =IF($B$4="All products",SUMIFS('Monthly Source'!$E$8:$E$55,'Monthly Source'!$A$8:$A$55,$A16),SUMIFS('Monthly Source'!$E$8:$E$55,'Monthly Source'!$A$8:$A$55,$A16,'Monthly Source'!$B$8:$B$55,$B$4)) -> 12909 | E16: =IF(D16=0,"n.a.",C16/D16) -> 0.99604927 | F16: =IF(B15=0,"n.a.",B16/B15-1) -> 0.064571994 | G16: =TEXT(A16,"mmm yyyy") -> May 2025 | I16: Expected known | J16: 351490
A17: 2025-06-01T00:00:00.000Z | B17: =IF($B$4="All products",SUMIFS('Monthly Source'!$C$8:$C$55,'Monthly Source'!$A$8:$A$55,$A17),SUMIFS('Monthly Source'!$C$8:$C$55,'Monthly Source'!$A$8:$A$55,$A17,'Monthly Source'!$B$8:$B$55,$B$4)) -> 12921 | C17: =IF($B$4="All products",SUMIFS('Monthly Source'!$D$8:$D$55,'Monthly Source'!$A$8:$A$55,$A17),SUMIFS('Monthly Source'!$D$8:$D$55,'Monthly Source'!$A$8:$A$55,$A17,'Monthly Source'!$B$8:$B$55,$B$4)) -> 12747 | D17: =IF($B$4="All products",SUMIFS('Monthly Source'!$E$8:$E$55,'Monthly Source'!$A$8:$A$55,$A17),SUMIFS('Monthly Source'!$E$8:$E$55,'Monthly Source'!$A$8:$A$55,$A17,'Monthly Source'!$B$8:$B$55,$B$4)) -> 12921 | E17: =IF(D17=0,"n.a.",C17/D17) -> 0.98653355 | F17: =IF(B16=0,"n.a.",B17/B16-1) -> 0.00092958401 | G17: =TEXT(A17,"mmm yyyy") -> Jun 2025
A18: 2025-07-01T00:00:00.000Z | B18: =IF($B$4="All products",SUMIFS('Monthly Source'!$C$8:$C$55,'Monthly Source'!$A$8:$A$55,$A18),SUMIFS('Monthly Source'!$C$8:$C$55,'Monthly Source'!$A$8:$A$55,$A18,'Monthly Source'!$B$8:$B$55,$B$4)) -> 14508 | C18: =IF($B$4="All products",SUMIFS('Monthly Source'!$D$8:$D$55,'Monthly Source'!$A$8:$A$55,$A18),SUMIFS('Monthly Source'!$D$8:$D$55,'Monthly Source'!$A$8:$A$55,$A18,'Monthly Source'!$B$8:$B$55,$B$4)) -> 14400 | D18: =IF($B$4="All products",SUMIFS('Monthly Source'!$E$8:$E$55,'Monthly Source'!$A$8:$A$55,$A18),SUMIFS('Monthly Source'!$E$8:$E$55,'Monthly Source'!$A$8:$A$55,$A18,'Monthly Source'!$B$8:$B$55,$B$4)) -> 14508 | E18: =IF(D18=0,"n.a.",C18/D18) -> 0.99255583 | F18: =IF(B17=0,"n.a.",B18/B17-1) -> 0.12282331 | G18: =TEXT(A18,"mmm yyyy") -> Jul 2025 | I18: Count difference | J18: =SUM('Monthly Source'!C8:C55)-J14 -> 0
A19: 2025-08-01T00:00:00.000Z | B19: =IF($B$4="All products",SUMIFS('Monthly Source'!$C$8:$C$55,'Monthly Source'!$A$8:$A$55,$A19),SUMIFS('Monthly Source'!$C$8:$C$55,'Monthly Source'!$A$8:$A$55,$A19,'Monthly Source'!$B$8:$B$55,$B$4)) -> 14424 | C19: =IF($B$4="All products",SUMIFS('Monthly Source'!$D$8:$D$55,'Monthly Source'!$A$8:$A$55,$A19),SUMIFS('Monthly Source'!$D$8:$D$55,'Monthly Source'!$A$8:$A$55,$A19,'Monthly Source'!$B$8:$B$55,$B$4)) -> 14351 | D19: =IF($B$4="All products",SUMIFS('Monthly Source'!$E$8:$E$55,'Monthly Source'!$A$8:$A$55,$A19),SUMIFS('Monthly Source'!$E$8:$E$55,'Monthly Source'!$A$8:$A$55,$A19,'Monthly Source'!$B$8:$B$55,$B$4)) -> 14424 | E19: =IF(D19=0,"n.a.",C19/D19) -> 0.99493899 | F19: =IF(B18=0,"n.a.",B19/B18-1) -> -0.005789909 | G19: =TEXT(A19,"mmm yyyy") -> Aug 2025 | I19: Yes difference | J19: =SUM('Monthly Source'!D8:D55)-J15 -> 0
A20: 2025-09-01T00:00:00.000Z | B20: =IF($B$4="All products",SUMIFS('Monthly Source'!$C$8:$C$55,'Monthly Source'!$A$8:$A$55,$A20),SUMIFS('Monthly Source'!$C$8:$C$55,'Monthly Source'!$A$8:$A$55,$A20,'Monthly Source'!$B$8:$B$55,$B$4)) -> 14645 | C20: =IF($B$4="All products",SUMIFS('Monthly Source'!$D$8:$D$55,'Monthly Source'!$A$8:$A$55,$A20),SUMIFS('Monthly Source'!$D$8:$D$55,'Monthly Source'!$A$8:$A$55,$A20,'Monthly Source'!$B$8:$B$55,$B$4)) -> 14587 | D20: =IF($B$4="All products",SUMIFS('Monthly Source'!$E$8:$E$55,'Monthly Source'!$A$8:$A$55,$A20),SUMIFS('Monthly Source'!$E$8:$E$55,'Monthly Source'!$A$8:$A$55,$A20,'Monthly Source'!$B$8:$B$55,$B$4)) -> 14645 | E20: =IF(D20=0,"n.a.",C20/D20) -> 0.9960396 | F20: =IF(B19=0,"n.a.",B20/B19-1) -> 0.015321686 | G20: =TEXT(A20,"mmm yyyy") -> Sep 2025 | I20: Known difference | J20: =SUM('Monthly Source'!E8:E55)-J16 -> 0
A21: 2025-10-01T00:00:00.000Z | B21: =IF($B$4="All products",SUMIFS('Monthly Source'!$C$8:$C$55,'Monthly Source'!$A$8:$A$55,$A21),SUMIFS('Monthly Source'!$C$8:$C$55,'Monthly Source'!$A$8:$A$55,$A21,'Monthly Source'!$B$8:$B$55,$B$4)) -> 13721 | C21: =IF($B$4="All products",SUMIFS('Monthly Source'!$D$8:$D$55,'Monthly Source'!$A$8:$A$55,$A21),SUMIFS('Monthly Source'!$D$8:$D$55,'Monthly Source'!$A$8:$A$55,$A21,'Monthly Source'!$B$8:$B$55,$B$4)) -> 13668 | D21: =IF($B$4="All products",SUMIFS('Monthly Source'!$E$8:$E$55,'Monthly Source'!$A$8:$A$55,$A21),SUMIFS('Monthly Source'!$E$8:$E$55,'Monthly Source'!$A$8:$A$55,$A21,'Monthly Source'!$B$8:$B$55,$B$4)) -> 13721 | E21: =IF(D21=0,"n.a.",C21/D21) -> 0.99613731 | F21: =IF(B20=0,"n.a.",B21/B20-1) -> -0.063093206 | G21: =TEXT(A21,"mmm yyyy") -> Oct 2025
A22: 2025-11-01T00:00:00.000Z | B22: =IF($B$4="All products",SUMIFS('Monthly Source'!$C$8:$C$55,'Monthly Source'!$A$8:$A$55,$A22),SUMIFS('Monthly Source'!$C$8:$C$55,'Monthly Source'!$A$8:$A$55,$A22,'Monthly Source'!$B$8:$B$55,$B$4)) -> 12938 | C22: =IF($B$4="All products",SUMIFS('Monthly Source'!$D$8:$D$55,'Monthly Source'!$A$8:$A$55,$A22),SUMIFS('Monthly Source'!$D$8:$D$55,'Monthly Source'!$A$8:$A$55,$A22,'Monthly Source'!$B$8:$B$55,$B$4)) -> 12850 | D22: =IF($B$4="All products",SUMIFS('Monthly Source'!$E$8:$E$55,'Monthly Source'!$A$8:$A$55,$A22),SUMIFS('Monthly Source'!$E$8:$E$55,'Monthly Source'!$A$8:$A$55,$A22,'Monthly Source'!$B$8:$B$55,$B$4)) -> 12938 | E22: =IF(D22=0,"n.a.",C22/D22) -> 0.99319833 | F22: =IF(B21=0,"n.a.",B22/B21-1) -> -0.057065812 | G22: =TEXT(A22,"mmm yyyy") -> Nov 2025
A23: 2025-12-01T00:00:00.000Z | B23: =IF($B$4="All products",SUMIFS('Monthly Source'!$C$8:$C$55,'Monthly Source'!$A$8:$A$55,$A23),SUMIFS('Monthly Source'!$C$8:$C$55,'Monthly Source'!$A$8:$A$55,$A23,'Monthly Source'!$B$8:$B$55,$B$4)) -> 15551 | C23: =IF($B$4="All products",SUMIFS('Monthly Source'!$D$8:$D$55,'Monthly Source'!$A$8:$A$55,$A23),SUMIFS('Monthly Source'!$D$8:$D$55,'Monthly Source'!$A$8:$A$55,$A23,'Monthly Source'!$B$8:$B$55,$B$4)) -> 15404 | D23: =IF($B$4="All products",SUMIFS('Monthly Source'!$E$8:$E$55,'Monthly Source'!$A$8:$A$55,$A23),SUMIFS('Monthly Source'!$E$8:$E$55,'Monthly Source'!$A$8:$A$55,$A23,'Monthly Source'!$B$8:$B$55,$B$4)) -> 15551 | E23: =IF(D23=0,"n.a.",C23/D23) -> 0.99054723 | F23: =IF(B22=0,"n.a.",B23/B22-1) -> 0.20196321 | G23: =TEXT(A23,"mmm yyyy") -> Dec 2025
A24: 2026-01-01T00:00:00.000Z | B24: =IF($B$4="All products",SUMIFS('Monthly Source'!$C$8:$C$55,'Monthly Source'!$A$8:$A$55,$A24),SUMIFS('Monthly Source'!$C$8:$C$55,'Monthly Source'!$A$8:$A$55,$A24,'Monthly Source'!$B$8:$B$55,$B$4)) -> 17432 | C24: =IF($B$4="All products",SUMIFS('Monthly Source'!$D$8:$D$55,'Monthly Source'!$A$8:$A$55,$A24),SUMIFS('Monthly Source'!$D$8:$D$55,'Monthly Source'!$A$8:$A$55,$A24,'Monthly Source'!$B$8:$B$55,$B$4)) -> 17277 | D24: =IF($B$4="All products",SUMIFS('Monthly Source'!$E$8:$E$55,'Monthly Source'!$A$8:$A$55,$A24),SUMIFS('Monthly Source'!$E$8:$E$55,'Monthly Source'!$A$8:$A$55,$A24,'Monthly Source'!$B$8:$B$55,$B$4)) -> 17432 | E24: =IF(D24=0,"n.a.",C24/D24) -> 0.99110831 | F24: =IF(B23=0,"n.a.",B24/B23-1) -> 0.12095685 | G24: =TEXT(A24,"mmm yyyy") -> Jan 2026
A25: 2026-02-01T00:00:00.000Z | B25: =IF($B$4="All products",SUMIFS('Monthly Source'!$C$8:$C$55,'Monthly Source'!$A$8:$A$55,$A25),SUMIFS('Monthly Source'!$C$8:$C$55,'Monthly Source'!$A$8:$A$55,$A25,'Monthly Source'!$B$8:$B$55,$B$4)) -> 13960 | C25: =IF($B$4="All products",SUMIFS('Monthly Source'!$D$8:$D$55,'Monthly Source'!$A$8:$A$55,$A25),SUMIFS('Monthly Source'!$D$8:$D$55,'Monthly Source'!$A$8:$A$55,$A25,'Monthly Source'!$B$8:$B$55,$B$4)) -> 13783 | D25: =IF($B$4="All products",SUMIFS('Monthly Source'!$E$8:$E$55,'Monthly Source'!$A$8:$A$55,$A25),SUMIFS('Monthly Source'!$E$8:$E$55,'Monthly Source'!$A$8:$A$55,$A25,'Monthly Source'!$B$8:$B$55,$B$4)) -> 13960 | E25: =IF(D25=0,"n.a.",C25/D25) -> 0.98732092 | F25: =IF(B24=0,"n.a.",B25/B24-1) -> -0.19917393 | G25: =TEXT(A25,"mmm yyyy") -> Feb 2026
A26: 2026-03-01T00:00:00.000Z | B26: =IF($B$4="All products",SUMIFS('Monthly Source'!$C$8:$C$55,'Monthly Source'!$A$8:$A$55,$A26),SUMIFS('Monthly Source'!$C$8:$C$55,'Monthly Source'!$A$8:$A$55,$A26,'Monthly Source'!$B$8:$B$55,$B$4)) -> 16151 | C26: =IF($B$4="All products",SUMIFS('Monthly Source'!$D$8:$D$55,'Monthly Source'!$A$8:$A$55,$A26),SUMIFS('Monthly Source'!$D$8:$D$55,'Monthly Source'!$A$8:$A$55,$A26,'Monthly Source'!$B$8:$B$55,$B$4)) -> 15982 | D26: =IF($B$4="All products",SUMIFS('Monthly Source'!$E$8:$E$55,'Monthly Source'!$A$8:$A$55,$A26),SUMIFS('Monthly Source'!$E$8:$E$55,'Monthly Source'!$A$8:$A$55,$A26,'Monthly Source'!$B$8:$B$55,$B$4)) -> 16151 | E26: =IF(D26=0,"n.a.",C26/D26) -> 0.98953625 | F26: =IF(B25=0,"n.a.",B26/B25-1) -> 0.15694842 | G26: =TEXT(A26,"mmm yyyy") -> Mar 2026
A27: 2026-04-01T00:00:00.000Z | B27: =IF($B$4="All products",SUMIFS('Monthly Source'!$C$8:$C$55,'Monthly Source'!$A$8:$A$55,$A27),SUMIFS('Monthly Source'!$C$8:$C$55,'Monthly Source'!$A$8:$A$55,$A27,'Monthly Source'!$B$8:$B$55,$B$4)) -> 15904 | C27: =IF($B$4="All products",SUMIFS('Monthly Source'!$D$8:$D$55,'Monthly Source'!$A$8:$A$55,$A27),SUMIFS('Monthly Source'!$D$8:$D$55,'Monthly Source'!$A$8:$A$55,$A27,'Monthly Source'!$B$8:$B$55,$B$4)) -> 15703 | D27: =IF($B$4="All products",SUMIFS('Monthly Source'!$E$8:$E$55,'Monthly Source'!$A$8:$A$55,$A27),SUMIFS('Monthly Source'!$E$8:$E$55,'Monthly Source'!$A$8:$A$55,$A27,'Monthly Source'!$B$8:$B$55,$B$4)) -> 15904 | E27: =IF(D27=0,"n.a.",C27/D27) -> 0.98736167 | F27: =IF(B26=0,"n.a.",B27/B26-1) -> -0.015293171 | G27: =TEXT(A27,"mmm yyyy") -> Apr 2026
A28: 2026-05-01T00:00:00.000Z | B28: =IF($B$4="All products",SUMIFS('Monthly Source'!$C$8:$C$55,'Monthly Source'!$A$8:$A$55,$A28),SUMIFS('Monthly Source'!$C$8:$C$55,'Monthly Source'!$A$8:$A$55,$A28,'Monthly Source'!$B$8:$B$55,$B$4)) -> 15123 | C28: =IF($B$4="All products",SUMIFS('Monthly Source'!$D$8:$D$55,'Monthly Source'!$A$8:$A$55,$A28),SUMIFS('Monthly Source'!$D$8:$D$55,'Monthly Source'!$A$8:$A$55,$A28,'Monthly Source'!$B$8:$B$55,$B$4)) -> 14902 | D28: =IF($B$4="All products",SUMIFS('Monthly Source'!$E$8:$E$55,'Monthly Source'!$A$8:$A$55,$A28),SUMIFS('Monthly Source'!$E$8:$E$55,'Monthly Source'!$A$8:$A$55,$A28,'Monthly Source'!$B$8:$B$55,$B$4)) -> 15123 | E28: =IF(D28=0,"n.a.",C28/D28) -> 0.9853865 | F28: =IF(B27=0,"n.a.",B28/B27-1) -> -0.049107143 | G28: =TEXT(A28,"mmm yyyy") -> May 2026
A29: 2026-06-01T00:00:00.000Z | B29: =IF($B$4="All products",SUMIFS('Monthly Source'!$C$8:$C$55,'Monthly Source'!$A$8:$A$55,$A29),SUMIFS('Monthly Source'!$C$8:$C$55,'Monthly Source'!$A$8:$A$55,$A29,'Monthly Source'!$B$8:$B$55,$B$4)) -> 15139 | C29: =IF($B$4="All products",SUMIFS('Monthly Source'!$D$8:$D$55,'Monthly Source'!$A$8:$A$55,$A29),SUMIFS('Monthly Source'!$D$8:$D$55,'Monthly Source'!$A$8:$A$55,$A29,'Monthly Source'!$B$8:$B$55,$B$4)) -> 14926 | D29: =IF($B$4="All products",SUMIFS('Monthly Source'!$E$8:$E$55,'Monthly Source'!$A$8:$A$55,$A29),SUMIFS('Monthly Source'!$E$8:$E$55,'Monthly Source'!$A$8:$A$55,$A29,'Monthly Source'!$B$8:$B$55,$B$4)) -> 15139 | E29: =IF(D29=0,"n.a.",C29/D29) -> 0.98593038 | F29: =IF(B28=0,"n.a.",B29/B28-1) -> 0.0010579911 | G29: =TEXT(A29,"mmm yyyy") -> Jun 2026
A30: 2026-07-01T00:00:00.000Z | B30: =IF($B$4="All products",SUMIFS('Monthly Source'!$C$8:$C$55,'Monthly Source'!$A$8:$A$55,$A30),SUMIFS('Monthly Source'!$C$8:$C$55,'Monthly Source'!$A$8:$A$55,$A30,'Monthly Source'!$B$8:$B$55,$B$4)) -> 16123 | C30: =IF($B$4="All products",SUMIFS('Monthly Source'!$D$8:$D$55,'Monthly Source'!$A$8:$A$55,$A30),SUMIFS('Monthly Source'!$D$8:$D$55,'Monthly Source'!$A$8:$A$55,$A30,'Monthly Source'!$B$8:$B$55,$B$4)) -> 15934 | D30: =IF($B$4="All products",SUMIFS('Monthly Source'!$E$8:$E$55,'Monthly Source'!$A$8:$A$55,$A30),SUMIFS('Monthly Source'!$E$8:$E$55,'Monthly Source'!$A$8:$A$55,$A30,'Monthly Source'!$B$8:$B$55,$B$4)) -> 16123 | E30: =IF(D30=0,"n.a.",C30/D30) -> 0.98827762 | F30: =IF(B29=0,"n.a.",B30/B29-1) -> 0.064997688 | G30: =TEXT(A30,"mmm yyyy") -> Jul 2026
A31: 2026-08-01T00:00:00.000Z | B31: =IF($B$4="All products",SUMIFS('Monthly Source'!$C$8:$C$55,'Monthly Source'!$A$8:$A$55,$A31),SUMIFS('Monthly Source'!$C$8:$C$55,'Monthly Source'!$A$8:$A$55,$A31,'Monthly Source'!$B$8:$B$55,$B$4)) -> 16201 | C31: =IF($B$4="All products",SUMIFS('Monthly Source'!$D$8:$D$55,'Monthly Source'!$A$8:$A$55,$A31),SUMIFS('Monthly Source'!$D$8:$D$55,'Monthly Source'!$A$8:$A$55,$A31,'Monthly Source'!$B$8:$B$55,$B$4)) -> 16105 | D31: =IF($B$4="All products",SUMIFS('Monthly Source'!$E$8:$E$55,'Monthly Source'!$A$8:$A$55,$A31),SUMIFS('Monthly Source'!$E$8:$E$55,'Monthly Source'!$A$8:$A$55,$A31,'Monthly Source'!$B$8:$B$55,$B$4)) -> 16201 | E31: =IF(D31=0,"n.a.",C31/D31) -> 0.99407444 | F31: =IF(B30=0,"n.a.",B31/B30-1) -> 0.0048378093 | G31: =TEXT(A31,"mmm yyyy") -> Aug 2026
A32: 2026-09-01T00:00:00.000Z | B32: =IF($B$4="All products",SUMIFS('Monthly Source'!$C$8:$C$55,'Monthly Source'!$A$8:$A$55,$A32),SUMIFS('Monthly Source'!$C$8:$C$55,'Monthly Source'!$A$8:$A$55,$A32,'Monthly Source'!$B$8:$B$55,$B$4)) -> 16651 | C32: =IF($B$4="All products",SUMIFS('Monthly Source'!$D$8:$D$55,'Monthly Source'!$A$8:$A$55,$A32),SUMIFS('Monthly Source'!$D$8:$D$55,'Monthly Source'!$A$8:$A$55,$A32,'Monthly Source'!$B$8:$B$55,$B$4)) -> 16611 | D32: =IF($B$4="All products",SUMIFS('Monthly Source'!$E$8:$E$55,'Monthly Source'!$A$8:$A$55,$A32),SUMIFS('Monthly Source'!$E$8:$E$55,'Monthly Source'!$A$8:$A$55,$A32,'Monthly Source'!$B$8:$B$55,$B$4)) -> 16651 | E32: =IF(D32=0,"n.a.",C32/D32) -> 0.99759774 | F32: =IF(B31=0,"n.a.",B32/B31-1) -> 0.027776063 | G32: =TEXT(A32,"mmm yyyy") -> Sep 2026
A35: Total / weighted rate | B35: =SUM(B9:B32) -> 351490 | C35: =SUM(C9:C32) -> 348983 | D35: =SUM(D9:D32) -> 351490 | E35: =IF(D35=0,"n.a.",C35/D35) -> 0.99286751

Sheet Capacity
A2: Review capacity · weekly scenario
A4: Illustrative review effort; historical not-timely records are not a live unresolved backlog.
A6: Review month | B6: 2026-09-01T00:00:00.000Z | D6: Available minutes | E6: =IF(COUNT(B9:B12)<>4,"n.a.",IF(OR(B9<0,B10<0,B11<=0,B12<=0,B12>1),"n.a.",B9*B10*60*B12)) -> 1800
A7: Selected records | B7: =SUMIFS('Monthly Source'!$F$8:$F$55,'Monthly Source'!$A$8:$A$55,B6) -> 40 | D7: Minutes per review | E7: =IF(ISNUMBER(B11),B11,"n.a.") -> 30
D8: Weekly capacity | E8: =IF(ISNUMBER(E6),INT(E6/E7),"n.a.") -> 60
A9: Reviewers | B9: 2 | D9: Reviewable records | E9: =IF(ISNUMBER(E8),MIN(B7,E8),"n.a.") -> 40 | J9: Amber cells are editable.
A10: Hours / reviewer | B10: 20 | D10: Remaining records | E10: =IF(ISNUMBER(E8),MAX(0,B7-E8),"n.a.") -> 0
A11: Minutes / review | B11: 30 | D11: Review effort (hours) | E11: =IF(AND(ISNUMBER(B11),B11>0),B7*B11/60,"n.a.") -> 20 | J11: No source data is changed.
A12: Productive time | B12: 0.75 | D12: Input status | E12: =IF(ISNUMBER(E8),"Inputs valid","Enter valid inputs") -> Inputs valid

Sheet Pivot Analysis
A2: Pivot analysis · monthly complaints
A4: Native PivotTable: product filter and slicer, month rows, summed complaints. Source: all 48 monthly aggregates.
A6: Product | B6: (All)
A8: Month | B8: Complaints
A9: Oct 2024 | B9: 11868
A10: Nov 2024 | B10: 11270
A11: Dec 2024 | B11: 11495
A12: Jan 2025 | B12: 27440
A13: Feb 2025 | B13: 11665
A14: Mar 2025 | B14: 11325
A15: Apr 2025 | B15: 12126
A16: May 2025 | B16: 12909
A17: Jun 2025 | B17: 12921
A18: Jul 2025 | B18: 14508
A19: Aug 2025 | B19: 14424
A20: Sep 2025 | B20: 14645
... A33: Grand Total | B33: 351490

Sheet Detail
A2: Detail · 500-record demonstration extract
A4: Newest complete-month records; not a representative sample. Full-population analysis uses Monthly Source.
A5: Source: CFPB Consumer Complaint Database, 2026-10-19; original IDs preserved as text.
A7: Complaint ID | B7: Received | C7: Product | D7: Issue | E7: Company | F7: State | G7: Timely | H7: Response | I7: Channel | J7: Sent | K7: Sub-product | L7: Sub-issue | M7: Review team (simulated) | N7: Received month
A8: 28629347 | B8: 2026-09-30T00:00:00.000Z | C8: Credit card | D8: Problem with a purchase shown on your statement | E8: WELLS FARGO & COMPANY | F8: TX | G8: Yes | H8: Closed with explanation | I8: Web | J8: 2026-09-30T00:00:00.000Z | K8: General-purpose credit card or charge card | L8: Card was charged for something you did not purchase with the card | M8: =_xlfn.XLOOKUP(C8,'Lookups'!$A$7:$A$8,'Lookups'!$B$7:$B$8,"Unmapped",0) -> Card operations | N8: =DATE(YEAR(B8),MONTH(B8),1) -> 46266
A9: 28630300 | B9: 2026-09-30T00:00:00.000Z | C9: Checking or savings account | D9: Managing an account | E9: NAVY FEDERAL CREDIT UNION | F9: NJ | G9: Yes | H9: In progress | I9: Web | J9: 2026-09-30T00:00:00.000Z | K9: Savings account | L9: Problem making or receiving payments | M9: =_xlfn.XLOOKUP(C9,'Lookups'!$A$7:$A$8,'Lookups'!$B$7:$B$8,"Unmapped",0) -> Deposit operations | N9: =DATE(YEAR(B9),MONTH(B9),1) -> 46266
A10: 28630505 | B10: 2026-09-30T00:00:00.000Z | C10: Credit card | D10: Other features, terms, or problems | E10: JPMORGAN CHASE & CO. | F10: GA | G10: Yes | H10: Closed with explanation | I10: Web | J10: 2026-09-30T00:00:00.000Z | K10: General-purpose credit card or charge card | L10: Other problem | M10: =_xlfn.XLOOKUP(C10,'Lookups'!$A$7:$A$8,'Lookups'!$B$7:$B$8,"Unmapped",0) -> Card operations | N10: =DATE(YEAR(B10),MONTH(B10),1) -> 46266
A11: 28630843 | B11: 2026-09-30T00:00:00.000Z | C11: Credit card | D11: Problem when making payments | E11: SYNCHRONY FINANCIAL | F11: FL | G11: Yes | H11: Closed with explanation | I11: Web | J11: 2026-09-30T00:00:00.000Z | K11: Store credit card | L11: Problem during payment process | M11: =_xlfn.XLOOKUP(C11,'Lookups'!$A$7:$A$8,'Lookups'!$B$7:$B$8,"Unmapped",0) -> Card operations | N11: =DATE(YEAR(B11),MONTH(B11),1) -> 46266
A12: 28631149 | B12: 2026-09-30T00:00:00.000Z | C12: Checking or savings account | D12: Managing an account | E12: SOFI TECHNOLOGIES, INC. | F12: CT | G12: Yes | H12: Closed with explanation | I12: Web | J12: 2026-09-30T00:00:00.000Z | K12: Savings account | L12: Problem accessing account | M12: =_xlfn.XLOOKUP(C12,'Lookups'!$A$7:$A$8,'Lookups'!$B$7:$B$8,"Unmapped",0) -> Deposit operations | N12: =DATE(YEAR(B12),MONTH(B12),1) -> 46266
A13: 28631245 | B13: 2026-09-30T00:00:00.000Z | C13: Credit card | D13: Getting a credit card | E13: GOLDMAN SACHS BANK USA | F13: IL | G13: Yes | H13: Closed with explanation | I13: Web | J13: 2026-09-30T00:00:00.000Z | K13: General-purpose credit card or charge card | L13: Card opened without my consent or knowledge | M13: =_xlfn.XLOOKUP(C13,'Lookups'!$A$7:$A$8,'Lookups'!$B$7:$B$8,"Unmapped",0) -> Card operations | N13: =DATE(YEAR(B13),MONTH(B13),1) -> 46266
A14: 28631323 | B14: 2026-09-30T00:00:00.000Z | C14: Credit card | D14: Getting a credit card | E14: EQUIFAX, INC. | F14: CA | G14: Yes | H14: Closed with explanation | I14: Web | J14: 2026-09-30T00:00:00.000Z | K14: General-purpose credit card or charge card | L14: Card opened without my consent or knowledge | M14: =_xlfn.XLOOKUP(C14,'Lookups'!$A$7:$A$8,'Lookups'!$B$7:$B$8,"Unmapped",0) -> Card operations | N14: =DATE(YEAR(B14),MONTH(B14),1) -> 46266
A15: 28631463 | B15: 2026-09-30T00:00:00.000Z | C15: Checking or savings account | D15: Closing an account | E15: BANK OF AMERICA, NATIONAL ASSOCIATION | F15: TX | G15: Yes | H15: In progress | I15: Web | J15: 2026-09-30T00:00:00.000Z | K15: Checking account | L15: Company closed your account | M15: =_xlfn.XLOOKUP(C15,'Lookups'!$A$7:$A$8,'Lookups'!$B$7:$B$8,"Unmapped",0) -> Deposit operations | N15: =DATE(YEAR(B15),MONTH(B15),1) -> 46266
A16: 28631465 | B16: 2026-09-30T00:00:00.000Z | C16: Checking or savings account | D16: Managing an account | E16: BANK OF AMERICA, NATIONAL ASSOCIATION | F16: VI | G16: Yes | H16: In progress | I16: Web | J16: 2026-09-30T00:00:00.000Z | K16: Checking account | L16: Problem accessing account | M16: =_xlfn.XLOOKUP(C16,'Lookups'!$A$7:$A$8,'Lookups'!$B$7:$B$8,"Unmapped",0) -> Deposit operations | N16: =DATE(YEAR(B16),MONTH(B16),1) -> 46266
A17: 28632043 | B17: 2026-09-30T00:00:00.000Z | C17: Credit card | D17: Problem with a purchase shown on your statement | E17: WELLS FARGO & COMPANY | F17: TX | G17: Yes | H17: In progress | I17: Web | J17: 2026-09-30T00:00:00.000Z | K17: General-purpose credit card or charge card | L17: Overcharged for something you did purchase with the card | M17: =_xlfn.XLOOKUP(C17,'Lookups'!$A$7:$A$8,'Lookups'!$B$7:$B$8,"Unmapped",0) -> Card operations | N17: =DATE(YEAR(B17),MONTH(B17),1) -> 46266
A18: 28632606 | B18: 2026-09-30T00:00:00.000Z | C18: Credit card | D18: Advertising and marketing, including promotional offers | E18: CITIBANK, N.A. | F18: NC | G18: Yes | H18: Closed with explanation | I18: Web | J18: 2026-09-30T00:00:00.000Z | K18: General-purpose credit card or charge card | L18: Didn't receive advertised or promotional terms | M18: =_xlfn.XLOOKUP(C18,'Lookups'!$A$7:$A$8,'Lookups'!$B$7:$B$8,"Unmapped",0) -> Card operations | N18: =DATE(YEAR(B18),MONTH(B18),1) -> 46266
A19: 28632658 | B19: 2026-09-30T00:00:00.000Z | C19: Credit card | D19: Getting a credit card | E19: NAVY FEDERAL CREDIT UNION | F19: CA | G19: Yes | H19: In progress | I19: Web | J19: 2026-09-30T00:00:00.000Z | K19: General-purpose credit card or charge card | L19: Card opened without my consent or knowledge | M19: =_xlfn.XLOOKUP(C19,'Lookups'!$A$7:$A$8,'Lookups'!$B$7:$B$8,"Unmapped",0) -> Card operations | N19: =DATE(YEAR(B19),MONTH(B19),1) -> 46266
... A507: 28713666 | B507: 2026-09-30T00:00:00.000Z | C507: Credit card | D507: Incorrect information on your report | E507: BANK OF AMERICA, NATIONAL ASSOCIATION | F507: VA | G507: Yes | H507: In progress | I507: Web | J507: 2026-09-30T00:00:00.000Z | K507: General-purpose credit card or charge card | L507: Account status incorrect | M507: =_xlfn.XLOOKUP(C507,'Lookups'!$A$7:$A$8,'Lookups'!$B$7:$B$8,"Unmapped",0) -> Card operations | N507: =DATE(YEAR(B507),MONTH(B507),1) -> 46266

Sheet Monthly Source
A2: Monthly source · complete population
A4: Source: CFPB Consumer Complaint Database; retrieved 2026-10-19
A5: https://www.consumerfinance.gov/data-research/consumer-complaints/
A7: Month | B7: Product | C7: Complaints | D7: Timely Yes | E7: Known status | F7: Not timely | G7: Unknown | H7: Month label
A8: 2024-10-01T00:00:00.000Z | B8: Checking or savings account | C8: 4692 | D8: 4668 | E8: 4692 | F8: 24 | G8: 0 | H8: Oct 2024
A9: 2024-10-01T00:00:00.000Z | B9: Credit card | C9: 7176 | D9: 7165 | E9: 7176 | F9: 11 | G9: 0 | H9: Oct 2024
A10: 2024-11-01T00:00:00.000Z | B10: Checking or savings account | C10: 5175 | D10: 5155 | E10: 5175 | F10: 20 | G10: 0 | H10: Nov 2024
A11: 2024-11-01T00:00:00.000Z | B11: Credit card | C11: 6095 | D11: 6086 | E11: 6095 | F11: 9 | G11: 0 | H11: Nov 2024
A12: 2024-12-01T00:00:00.000Z | B12: Checking or savings account | C12: 4798 | D12: 4779 | E12: 4798 | F12: 19 | G12: 0 | H12: Dec 2024
A13: 2024-12-01T00:00:00.000Z | B13: Credit card | C13: 6697 | D13: 6688 | E13: 6697 | F13: 9 | G13: 0 | H13: Dec 2024
A14: 2025-01-01T00:00:00.000Z | B14: Checking or savings account | C14: 18367 | D14: 18329 | E14: 18367 | F14: 38 | G14: 0 | H14: Jan 2025
A15: 2025-01-01T00:00:00.000Z | B15: Credit card | C15: 9073 | D15: 9047 | E15: 9073 | F15: 26 | G15: 0 | H15: Jan 2025
A16: 2025-02-01T00:00:00.000Z | B16: Checking or savings account | C16: 5452 | D16: 5421 | E16: 5452 | F16: 31 | G16: 0 | H16: Feb 2025
A17: 2025-02-01T00:00:00.000Z | B17: Credit card | C17: 6213 | D17: 6198 | E17: 6213 | F17: 15 | G17: 0 | H17: Feb 2025
A18: 2025-03-01T00:00:00.000Z | B18: Checking or savings account | C18: 5070 | D18: 5044 | E18: 5070 | F18: 26 | G18: 0 | H18: Mar 2025
A19: 2025-03-01T00:00:00.000Z | B19: Credit card | C19: 6255 | D19: 6244 | E19: 6255 | F19: 11 | G19: 0 | H19: Mar 2025
... A55: 2026-09-01T00:00:00.000Z | B55: Credit card | C55: 8572 | D55: 8553 | E55: 8572 | F55: 19 | G55: 0 | H55: Sep 2026

Sheet Lookups
A2: Product mapping
A4: Review-team mapping is a fictional portfolio workflow assumption.
A6: Product | B6: Review team
A7: Credit card | B7: Card operations
A8: Checking or savings account | B8: Deposit operations

Sheet UAT
A2: User acceptance testing
A4: Human acceptance: pending. Developer test evidence is separate; no stakeholder sign-off is claimed.
A6: Test ID | B6: Requirement | C6: Scenario | D6: Steps | E6: Expected result | F6: Actual result | G6: Status | H6: Reviewer | I6: Evidence / defect | J6: Developer check reference
A7: UAT-01 | B7: R01 | C7: Complete-month scope | D7: Open Executive overview with default filters. Compare dates and total to reports/quality.json. | E7: 24 complete months and the complete-population count agree. Partial month is excluded. | G7: Not run | J7: test_source_to_marts_reconciliation
A8: UAT-02 | B8: R01 | C8: Partial month separation | D8: Read the partial-month note and compare its count to quality.json partial.complaints. | E8: Partial count agrees and is not added to the main count. | G8: Not run | J8: test_source_to_marts_reconciliation
A9: UAT-03 | B9: R02 | C9: Product selection | D9: Select Credit card only. Compare the displayed total with a matching SQL count. | E9: Only Credit card records and totals appear. | G9: Not run | J9: test_intersecting_filters
A10: UAT-04 | B10: R02 | C10: Empty product selection | D10: Remove both selected products in Executive overview. | E10: Count is zero, timely rate is n.a., and the page remains usable. | G10: Not run | J10: test_workspaces_filters_and_zero_capacity
A11: UAT-05 | B11: R02 | C11: Filter intersection | D11: Select a company, a state and a product. Download the matching records. | E11: Every exported row satisfies all three selections. | G11: Not run | J11: test_intersecting_filters
A12: UAT-06 | B12: R02 | C12: Inclusive date boundaries | D12: Select Jan 1 through Jan 31 of a source year. Compare export minimum/maximum and count with SQL. | E12: All eligible Jan 1 and Jan 31 records are included; February records are excluded. | G12: Not run | J12: test_inclusive_dates
A13: UAT-07 | B13: R03 | C13: Timeliness denominator | D13: On Response quality, divide Timely Yes by Known Status. Compare with the displayed percentage. | E13: Yes/(Yes+No) agrees to display precision; unknown records do not enter denominator. | G13: Not run | J13: test_rate_excludes_unknown
A14: UAT-08 | B14: R03 | C14: Unknown-only fixture | D14: Run the documented all-unknown fixture and inspect the result. | E14: Timely rate is unavailable, not zero or 100%. | G14: Not run | J14: test_all_unknown_rate_is_unavailable
A15: UAT-09 | B15: R04 | C15: Missing month fixture | D15: Execute missing-month fixture with Jan and March records only. | E15: February remains zero and March percentage change is unavailable after a zero baseline. | G15: Not run | J15: test_missing_month_and_zero_baseline
A16: UAT-10 | B16: R04 | C16: Rolling mean | D16: Use three complete displayed months; manually average their counts. | E16: Third-month rolling mean agrees; first two rolling values are unavailable. | G16: Not run | J16: test_missing_month_and_zero_baseline
A17: UAT-11 | B17: R05 | C17: Issue contribution reconciliation | D17: Select the last two complete months. Sum every issue change in the download. | E17: Sum equals comparison-month total less baseline total; waterfall Other issues preserves equality. | G17: Not run | J17: test_source_to_marts_reconciliation
A18: UAT-12 | B18: R05 | C18: New/disappearing issue fixture | D18: Run fixture containing one issue only in January and another only in March. | E18: Both issues appear; the new issue has no percentage baseline. | G18: Not run | J18: test_new_and_disappearing_issues
... A30: UAT-24 | B30: R12 | C30: Usability and navigation | D30: Open all five workspaces at normal browser size; inspect controls, captions and empty states. | E30: Navigation works; data definitions and context are visible; no application exceptions. | G30: Not run | J30: test_workspaces_filters_and_zero_capacity

Sheet Read Me
A2: Workbook guide
A5: Purpose | B5: Analyze published banking complaints and practice an auditable business analysis workflow.
A6: Source | B6: CFPB Consumer Complaint Database. https://www.consumerfinance.gov/data-research/consumer-complaints/
A7: Snapshot | B7: 2026-10-19; complete months 2024-10-01 to 2026-09.
A8: Population | B8: 351490 records across 24 complete months. Partial month excluded from analysis.
A9: Detail extract | B9: Newest 500 complete-month records. Not representative; do not extrapolate its percentages.
A10: Rates | B10: Timely Yes / (Yes + No). Unknown statuses remain separate. No resolution duration is inferred.
A11: Controls | B11: Analysis B4 selects product. Capacity B9:B12 are assumptions. Amber cells are editable.
A12: Lookups | B12: Detail uses XLOOKUP into the simulated team mapping. Identifiers remain text.
A13: Pivot | B13: Pivot Analysis contains a native PivotTable and product filter. Refresh it after source changes.
A14: Refresh | B14: Rebuild the pipeline and workbook from the frozen source, or replace matching source table rows and refresh calculations/pivots.
A15: UAT | B15: Human test statuses start Not run. Enter actual results, reviewer and evidence after executing a case.
A16: Limits | B16: Complaint counts are not customer incidence, market share, legal findings, or an unresolved backlog.
... A18: Verification | B18: Formula calculations, input changes, charts and workbook package structure are checked. See reports/excel_verification.json for native Excel verification status.
